ggerte12jhf/__init__.py
ggerte12jhf/custom.py
ggerte12jhf/functions.py
ggerte12jhf/helpers.py
ggerte12jhf/hints.py
ggerte12jhf/password.py
ggerte12jhf/requestiter.py
ggerte12jhf/sync.py
ggerte12jhf/types.py
ggerte12jhf/utils.py
ggerte12jhf/version.py
ggerte12jhf/_updates/__init__.py
ggerte12jhf/_updates/entitycache.py
ggerte12jhf/_updates/messagebox.py
ggerte12jhf/_updates/session.py
ggerte12jhf/client/__init__.py
ggerte12jhf/client/account.py
ggerte12jhf/client/auth.py
ggerte12jhf/client/bots.py
ggerte12jhf/client/buttons.py
ggerte12jhf/client/chats.py
ggerte12jhf/client/dialogs.py
ggerte12jhf/client/downloads.py
ggerte12jhf/client/media_handle.py
ggerte12jhf/client/messageparse.py
ggerte12jhf/client/messages.py
ggerte12jhf/client/telegrambaseclient.py
ggerte12jhf/client/telegramclient.py
ggerte12jhf/client/updates.py
ggerte12jhf/client/uploads.py
ggerte12jhf/client/users.py
ggerte12jhf/crypto/__init__.py
ggerte12jhf/crypto/aes.py
ggerte12jhf/crypto/aesctr.py
ggerte12jhf/crypto/authkey.py
ggerte12jhf/crypto/cdndecrypter.py
ggerte12jhf/crypto/factorization.py
ggerte12jhf/crypto/libssl.py
ggerte12jhf/crypto/rsa.py
ggerte12jhf/errors/__init__.py
ggerte12jhf/errors/common.py
ggerte12jhf/errors/rpcbaseerrors.py
ggerte12jhf/errors/rpcerrorlist.py
ggerte12jhf/events/__init__.py
ggerte12jhf/events/album.py
ggerte12jhf/events/callbackquery.py
ggerte12jhf/events/chataction.py
ggerte12jhf/events/common.py
ggerte12jhf/events/inlinequery.py
ggerte12jhf/events/messagedeleted.py
ggerte12jhf/events/messageedited.py
ggerte12jhf/events/messageread.py
ggerte12jhf/events/newmessage.py
ggerte12jhf/events/raw.py
ggerte12jhf/events/userupdate.py
ggerte12jhf/extensions/__init__.py
ggerte12jhf/extensions/binaryreader.py
ggerte12jhf/extensions/html.py
ggerte12jhf/extensions/markdown.py
ggerte12jhf/extensions/messagepacker.py
ggerte12jhf/network/__init__.py
ggerte12jhf/network/authenticator.py
ggerte12jhf/network/mtprotoplainsender.py
ggerte12jhf/network/mtprotosender.py
Teleggerte12jhfthon-0.1.1.dist-info/LICENSE
Teleggerte12jhfthon-0.1.1.dist-info/METADATA
Teleggerte12jhfthon-0.1.1.dist-info/WHEEL
Teleggerte12jhfthon-0.1.1.dist-info/top_level.txt
Teleggerte12jhfthon-0.1.1.dist-info/RECORD
