Metadata-Version: 2.1
Name: Teleggerte12jhfthon
Version: 0.1.1
Summary: Full-featured
Home-page: https://github.com/Lon4amiWe54bs/ggerte12jhf
Download-URL: https://github.com/Lon4amiW5ebs/ggerte12jhf/releases
Author: Copy
Author-email: copyscsc@hotmail.com
License: MIT
Keywords: telegram api chat client library messaging mtproto
Classifier: Development Status :: 5 - Production/Stable
Classifier: Intended Audience :: Developers
Classifier: Topic :: Communications :: Chat
Classifier: License :: OSI Approved :: MIT License
Classifier: Programming Language :: Python :: 3
Classifier: Programming Language :: Python :: 3.5
Classifier: Programming Language :: Python :: 3.6
Classifier: Programming Language :: Python :: 3.7
Classifier: Programming Language :: Python :: 3.8
Requires-Python: >=3.5
License-File: LICENSE
Requires-Dist: gmpy2
Requires-Dist: tgcrypto
Requires-Dist: rsa
Requires-Dist: pysocks
Requires-Dist: hachoir
Requires-Dist: pillow
Requires-Dist: aiohttp
